{
  "generated": "2026-05-14T08:31:51.152Z",
  "featureName": "BetterBond Commission Payments POC",
  "epicsScoped": 3,
  "totalEpics": 4,
  "coverage": {
    "functional": {
      "total": 27,
      "covered": 20,
      "uncovered": [
        "R17",
        "R18",
        "R19",
        "R20",
        "R21",
        "R22",
        "R23"
      ]
    },
    "businessRules": {
      "total": 10,
      "covered": 9,
      "uncovered": [
        "BR10"
      ]
    },
    "nonFunctional": {
      "total": 6,
      "covered": 6,
      "uncovered": []
    },
    "compliance": {
      "total": 0,
      "covered": 0,
      "uncovered": []
    },
    "overall": {
      "total": 43,
      "covered": 35,
      "percent": 81,
      "uncovered": [
        "R17",
        "R18",
        "R19",
        "R20",
        "R21",
        "R22",
        "R23",
        "BR10"
      ],
      "pending": [
        {
          "id": "R17",
          "claimedByEpic": 4
        },
        {
          "id": "R18",
          "claimedByEpic": 4
        },
        {
          "id": "R19",
          "claimedByEpic": 4
        },
        {
          "id": "R20",
          "claimedByEpic": 4
        },
        {
          "id": "R21",
          "claimedByEpic": 4
        },
        {
          "id": "R22",
          "claimedByEpic": 4
        },
        {
          "id": "R23",
          "claimedByEpic": 4
        },
        {
          "id": "BR10",
          "claimedByEpic": 4
        }
      ],
      "realGaps": []
    }
  },
  "epicGaps": {},
  "warnings": []
}